mkdocs_datosgobar/.DS_Store
mkdocs_datosgobar/__init__.py
mkdocs_datosgobar/__main__.py
mkdocs_datosgobar/md2pdf.py
mkdocs_datosgobar/datosgobar_docs/.DS_Store
mkdocs_datosgobar/datosgobar_docs/__init__.py
mkdocs_datosgobar/datosgobar_docs/main.html
mkdocs_datosgobar/datosgobar_docs/mkdocs_theme.yml
mkdocs_datosgobar/datosgobar_docs/assets/.DS_Store
mkdocs_datosgobar/datosgobar_docs/assets/fonts/font-awesome.css
mkdocs_datosgobar/datosgobar_docs/assets/fonts/material-icons.css
mkdocs_datosgobar/datosgobar_docs/assets/fonts/specimen/FontAwesome.ttf
mkdocs_datosgobar/datosgobar_docs/assets/fonts/specimen/FontAwesome.woff
mkdocs_datosgobar/datosgobar_docs/assets/fonts/specimen/FontAwesome.woff2
mkdocs_datosgobar/datosgobar_docs/assets/fonts/specimen/MaterialIcons-Regular.ttf
mkdocs_datosgobar/datosgobar_docs/assets/fonts/specimen/MaterialIcons-Regular.woff
mkdocs_datosgobar/datosgobar_docs/assets/fonts/specimen/MaterialIcons-Regular.woff2
mkdocs_datosgobar/datosgobar_docs/assets/images/.DS_Store
mkdocs_datosgobar/datosgobar_docs/assets/images/favicon.png
mkdocs_datosgobar/datosgobar_docs/assets/images/icons/bitbucket.1b09e088.svg
mkdocs_datosgobar/datosgobar_docs/assets/images/icons/github.f0b8504a.svg
mkdocs_datosgobar/datosgobar_docs/assets/images/icons/gitlab.6dd19c00.svg
mkdocs_datosgobar/datosgobar_docs/assets/javascripts/application.583bbe55.js
mkdocs_datosgobar/datosgobar_docs/assets/javascripts/modernizr.1aa3b519.js
mkdocs_datosgobar/datosgobar_docs/assets/javascripts/lunr/lunr.da.js
mkdocs_datosgobar/datosgobar_docs/assets/javascripts/lunr/lunr.de.js
mkdocs_datosgobar/datosgobar_docs/assets/javascripts/lunr/lunr.du.js
mkdocs_datosgobar/datosgobar_docs/assets/javascripts/lunr/lunr.es.js
mkdocs_datosgobar/datosgobar_docs/assets/javascripts/lunr/lunr.fi.js
mkdocs_datosgobar/datosgobar_docs/assets/javascripts/lunr/lunr.fr.js
mkdocs_datosgobar/datosgobar_docs/assets/javascripts/lunr/lunr.hu.js
mkdocs_datosgobar/datosgobar_docs/assets/javascripts/lunr/lunr.it.js
mkdocs_datosgobar-1.0.15.dist-info/LICENSE
mkdocs_datosgobar-1.0.15.dist-info/METADATA
mkdocs_datosgobar-1.0.15.dist-info/WHEEL
mkdocs_datosgobar-1.0.15.dist-info/entry_points.txt
mkdocs_datosgobar-1.0.15.dist-info/top_level.txt
mkdocs_datosgobar-1.0.15.dist-info/RECORD
