Metadata-Version: 2.1
Name: mkdocs-datosgobar
Version: 1.0.15
Summary: Temas de datosgobar para documentación con MkDocs
Home-page: http://www.mkdocs.org
Author: Datos Argentina
Author-email: datos@modernizacion.gob.ar
License: BSD
Platform: UNKNOWN
Requires-Python: >=2.7.9,!=3.0.*,!=3.1.*,!=3.2.*,!=3.3.*
Requires-Dist: mkdocs (>=1.0)
Requires-Dist: markdown
Requires-Dist: mkdocs-material
Requires-Dist: pymdown-extensions
Requires-Dist: pdfkit
Requires-Dist: bs4
Requires-Dist: unidecode
